setup.py
keras_rtst/__init__.py
keras_rtst/argparser.py
keras_rtst/main.py
keras_rtst/training.py
keras_rtst.egg-info/PKG-INFO
keras_rtst.egg-info/SOURCES.txt
keras_rtst.egg-info/dependency_links.txt
keras_rtst.egg-info/pbr.json
keras_rtst.egg-info/requires.txt
keras_rtst.egg-info/top_level.txt
keras_rtst/generators/__init__.py
keras_rtst/generators/base.py
keras_rtst/generators/callbacks.py
keras_rtst/generators/style_xfer.py
keras_rtst/models/__init__.py
keras_rtst/models/base.py
keras_rtst/models/config.py
keras_rtst/models/girthy.py
keras_rtst/models/patches.py
keras_rtst/models/regularizers.py
keras_rtst/models/style_xfer.py
keras_rtst/models/style_xfer_girthy.py
scripts/render-rtst.sh
scripts/rtst-download-training-images.sh
scripts/rtst-gif.sh
scripts/rtst.py
scripts/train-rtst.sh