Metadata-Version: 1.0
Name: keras-rtst
Version: 0.0.8
Summary: An implementation of real-time style transfer in Keras
Home-page: https://github.com/awentzonline/keras-rtst/
Author: Adam Wentz
Author-email: adam@adamwentz.com
License: UNKNOWN
Platform: UNKNOWN
